oneflow_onnx/__init__.py
oneflow_onnx/constants.py
oneflow_onnx/onnx_wrapper.py
oneflow_onnx/schemas.py
oneflow_onnx/util.py
oneflow_onnx/oneflow2onnx/__init__.py
oneflow_onnx/oneflow2onnx/flow2onnx.py
oneflow_onnx/oneflow2onnx/graph_builder.py
oneflow_onnx/oneflow2onnx/handler.py
oneflow_onnx/oneflow2onnx/util.py
oneflow_onnx/oneflow2onnx/handlers/__init__.py
oneflow_onnx/oneflow2onnx/handlers/array.py
oneflow_onnx/oneflow2onnx/handlers/common.py
oneflow_onnx/oneflow2onnx/handlers/math.py
oneflow_onnx/oneflow2onnx/handlers/misc.py
oneflow_onnx/oneflow2onnx/handlers/nn.py
oneflow_onnx/oneflow2onnx/handlers/quantize.py
oneflow_onnx/oneflow2onnx/handlers/reduce.py
oneflow_onnx/oneflow2onnx/optimizer/__init__.py
oneflow_onnx/oneflow2onnx/optimizer/back_to_back_optimizer.py
oneflow_onnx/oneflow2onnx/optimizer/const_fold_optimizer.py
oneflow_onnx/oneflow2onnx/optimizer/identity_optimizer.py
oneflow_onnx/oneflow2onnx/optimizer/loop_optimizer.py
oneflow_onnx/oneflow2onnx/optimizer/merge_duplicated_nodes_optimizer.py
oneflow_onnx/oneflow2onnx/optimizer/optimizer_base.py
oneflow_onnx/oneflow2onnx/optimizer/transpose_optimizer.py
oneflow_onnx-0.6.2.dist-info/METADATA
oneflow_onnx-0.6.2.dist-info/WHEEL
oneflow_onnx-0.6.2.dist-info/top_level.txt
oneflow_onnx-0.6.2.dist-info/RECORD
